{
  "_metadata": {
    "crawler_version": "1.0.0",
    "file_format_version": "1.0",
    "saved_at": "2026-01-12T09:41:28.626596"
  },
  "articles": [],
  "processed_at": "2026-01-12T09:41:28.626083",
  "subcategories": [
    "https://en.wikipedia.org/wiki/Category:Establishments_in_the_Straits_Settlements",
    "https://en.wikipedia.org/wiki/Category:Establishments_in_Singapore_by_decade",
    "https://en.wikipedia.org/wiki/Category:Establishments_in_Singapore_by_millennium",
    "https://en.wikipedia.org/wiki/Category:Establishments_in_Singapore_by_century",
    "https://en.wikipedia.org/wiki/Category:Establishments_in_Singapore_by_year",
    "https://en.wikipedia.org/wiki/Category:Singaporean_television_series_debuts"
  ],
  "title": "Establishments in Singapore",
  "type": "category",
  "url": "https://en.wikipedia.org/wiki/Category:Establishments_in_Singapore"
}