{
  "_metadata": {
    "crawler_version": "1.0.0",
    "file_format_version": "1.0",
    "saved_at": "2026-01-12T11:34:27.475875"
  },
  "content": "Malaysian singer **Marfuah Makarim** (1923 – 10 December 2015), better known by the stage name **Momo Latiff**, was an Indonesian-born Singaporean singer and actress who was active in the 1950s and 1960s. Her successful songs included \"Pantai Chinta Berahi\" (\"PCB\" beach, now Pantai Cahaya Bulan) to the music of pianist Dodo Mallinger. Originally a dancer, she was contracted as singer by [Shaw Brothers](/wiki/Shaw_Brothers) for films such as Putus Harapan (1955) and [Pendekar Bujang Lapok](/wiki/Pendekar_Bujang_Lapok) (1959). ## Early life Latiff was born Marfuah Makarim in 1923 in [Dutch East Indies](/wiki/Dutch_East_Indies). She moved to [Straits Settlements](/wiki/Straits_Settlements) in 1939, while in an Indonesian performing troupe on tour in the region. ## Career Latiff was discovered by an executive at [Shaw Brothers Studio](/wiki/Shaw_Brothers_Studio) which engaged her as a playback singer, leading her singing voice to be used in a movie. She was best known for her role as the wife of a martial arts master in *[Pendekar Bujang Lapok](/wiki/Pendekar_Bujang_Lapok)* (1959), co-starring [P. Ramlee](/wiki/P._Ramlee), [S. Shamsuddin](/wiki/S._Shamsuddin), and [Aziz Sattar](/wiki/Aziz_Sattar). ## Death On 9 December 2015, Latiff suffered from a high blood pressure and collapsed at her residence in [Woodlands](/wiki/Woodlands,_Singapore). She was rushed into [Khoo Teck Puat Hospital](/wiki/Khoo_Teck_Puat_Hospital) where she slipped into a coma due to burst in her brain blood vessel, and died next day at the age of 92. This article about a Singaporean singer is a stub. You can help Wikipedia by expanding it. - v - t - e\n",
  "language": "en",
  "processed_at": "2026-01-12T11:34:27.475434",
  "title": "Momo Latiff",
  "type": "article",
  "url": "https://en.wikipedia.org/wiki/Momo_Latiff"
}